LICENSE
MANIFEST.in
README.rst
setup.cfg
setup.py
pysoccer.egg-info/PKG-INFO
pysoccer.egg-info/SOURCES.txt
pysoccer.egg-info/dependency_links.txt
pysoccer.egg-info/entry_points.txt
pysoccer.egg-info/requires.txt
pysoccer.egg-info/top_level.txt
soccer/__init__.py
soccer/exceptions.py
soccer/main.py
soccer/request_handler.py
soccer/data/__init__.py
soccer/data/config.py
soccer/data/leagueids.py
soccer/data/leaguelists.py
soccer/data/leaguenames.py
soccer/data/leagueproperties.py
soccer/data/teamnames.py
soccer/data/urls.py
soccer/writers/__init__.py
soccer/writers/base.py
soccer/writers/team_writers.py
soccer/writers/writers.py