Metadata-Version: 1.1
Name: pysoccer
Version: 0.0.3
Summary: Soccer data for programmers.
Home-page: https://github.com/RayYu03/pysoccer
Author: RayYu03
Author-email: shiliuhuasheng@gmail.com
License: MIT
Keywords: soccer,football,football-data
Platform: UNKNOWN
Classifier: Development Status :: 3 - Alpha
Classifier: Environment :: Web Environment
Classifier: Intended Audience :: Information Technology
Classifier: Intended Audience :: End Users/Desktop
Classifier: License :: OSI Approved :: MIT License
Classifier: Operating System :: OS Independent
Classifier: Programming Language :: Python
Classifier: Topic :: Internet :: WWW/HTTP
Classifier: Programming Language :: Python :: 3 :: Only
